alibabacloud_dytnsapi20200217/__init__.py
alibabacloud_dytnsapi20200217/client.py
alibabacloud_dytnsapi20200217/models/__init__.py
alibabacloud_dytnsapi20200217/models/_cert_no_three_element_verification_request.py
alibabacloud_dytnsapi20200217/models/_cert_no_three_element_verification_response.py
alibabacloud_dytnsapi20200217/models/_cert_no_three_element_verification_response_body.py
alibabacloud_dytnsapi20200217/models/_cert_no_two_element_verification_request.py
alibabacloud_dytnsapi20200217/models/_cert_no_two_element_verification_response.py
alibabacloud_dytnsapi20200217/models/_cert_no_two_element_verification_response_body.py
alibabacloud_dytnsapi20200217/models/_company_four_elements_verification_request.py
alibabacloud_dytnsapi20200217/models/_company_four_elements_verification_response.py
alibabacloud_dytnsapi20200217/models/_company_four_elements_verification_response_body.py
alibabacloud_dytnsapi20200217/models/_company_three_elements_verification_request.py
alibabacloud_dytnsapi20200217/models/_company_three_elements_verification_response.py
alibabacloud_dytnsapi20200217/models/_company_three_elements_verification_response_body.py
alibabacloud_dytnsapi20200217/models/_company_two_elements_verification_request.py
alibabacloud_dytnsapi20200217/models/_company_two_elements_verification_response.py
alibabacloud_dytnsapi20200217/models/_company_two_elements_verification_response_body.py
alibabacloud_dytnsapi20200217/models/_delete_contacts_request.py
alibabacloud_dytnsapi20200217/models/_delete_contacts_response.py
alibabacloud_dytnsapi20200217/models/_delete_contacts_response_body.py
alibabacloud_dytnsapi20200217/models/_describe_empty_number_request.py
alibabacloud_dytnsapi20200217/models/_describe_empty_number_response.py
alibabacloud_dytnsapi20200217/models/_describe_empty_number_response_body.py
alibabacloud_dytnsapi20200217/models/_describe_mobile_operator_attribute_request.py
alibabacloud_dytnsapi20200217-3.2.0.dist-info/LICENSE
alibabacloud_dytnsapi20200217-3.2.0.dist-info/METADATA
alibabacloud_dytnsapi20200217-3.2.0.dist-info/WHEEL
alibabacloud_dytnsapi20200217-3.2.0.dist-info/top_level.txt
alibabacloud_dytnsapi20200217-3.2.0.dist-info/RECORD
